<connectorMetaData path="file">
	<name>File Reader</name>
	<author>Mirth Corporation</author>
	<pluginVersion>@mirthversion</pluginVersion>
	<mirthVersion>3.0.1</mirthVersion>
	<url>http://www.mirthcorp.com</url>
	<description>This connector allows Mirth to poll for files from a local or network file system.</description>
	<clientClassName>com.mirth.connect.connectors.file.FileReader</clientClassName>
	<serverClassName>com.mirth.connect.connectors.file.FileReceiver</serverClassName>
	<sharedClassName>com.mirth.connect.connectors.file.FileReceiverProperties</sharedClassName>
	<serviceClassName>com.mirth.connect.connectors.file.FileReaderService</serviceClassName>
	<library type="CLIENT" path="file-client.jar" />
	<library type="SHARED" path="file-shared.jar" />
	<library type="SERVER" path="file-server.jar" />
	<library type="SERVER" path="lib/jcifs-1.3.17.jar" />
	<library type="SERVER" path="lib/webdavclient4j-core-0.92.jar" />
	<protocol>file</protocol>
	<type>SOURCE</type>
</connectorMetaData>